cienpy/__init__.py
cienpy/buckling.py
cienpy/hollow_rectangular_section.py
cienpy/javascriptcodes.py
cienpy/models.py
cienpy/mohrcircle.py
cienpy/rectangular_section.py
cienpy/simplebeam.py
cienpy/stress_strain_elastic.py
cienpy/stress_strain_plastic.py
cienpy-0.1.1.dist-info/LICENSE
cienpy-0.1.1.dist-info/METADATA
cienpy-0.1.1.dist-info/WHEEL
cienpy-0.1.1.dist-info/top_level.txt
cienpy-0.1.1.dist-info/RECORD
