Metadata-Version: 2.1
Name: cienpy
Version: 0.1.1
Summary: A CIvil ENgineering PYthon package
Author-email: Carmine Schipani <schipanicarmine96@gmail.com>
License: MIT License        
Project-URL: Author, https://github.com/DonCammne
Project-URL: RESSLab, https://github.com/AlbanoCastroSousa/RESSPyLab
Classifier: Programming Language :: Python :: 3
Classifier: License :: OSI Approved :: MIT License
Classifier: Operating System :: OS Independent
Requires-Python: >=3.8
License-File: LICENSE
Requires-Dist: bokeh (>=2.4.2)
Requires-Dist: numpy
